czh_mod/__init__.py
czh_mod/apolloCommon/__init__.py
czh_mod/apolloCommon/commonNetgameApi.py
czh_mod/apolloCommon/extraMongoPool.py
czh_mod/apolloCommon/extraMysqlPool.py
czh_mod/apolloCommon/extraRedisPool.py
czh_mod/apolloCommon/mongoPool.py
czh_mod/apolloCommon/mysqlPool.py
czh_mod/apolloCommon/redisPool.py
czh_mod/apolloCommon/workerPool.py
czh_mod/lobby/__init__.py
czh_mod/lobby/netgameApi.py
czh_mod/lobbyGame/__init__.py
czh_mod/lobbyGame/netgameApi.py
czh_mod/lobbyGame/serverEvent.py
czh_mod/master/__init__.py
czh_mod/master/masterHttp.py
czh_mod/master/netgameApi.py
czh_mod/master/serverEvent.py
czh_mod/master/serverManager.py
czh_mod/mod/__init__.py
czh_mod/mod/client/__init__.py
czh_mod/mod/client/extraClientApi.py
czh_mod/mod/client/component/__init__.py
czh_mod/mod/client/component/actorCollidableCompClient.py
czh_mod/mod/client/component/actorMotionCompClient.py
czh_mod/mod/client/component/actorRenderCompClient.py
czh_mod/mod/client/component/attrCompClient.py
czh_mod/mod/client/component/audioCustomCompClient.py
czh_mod/mod/client/component/audioSystemCompClient.py
czh_mod/mod/client/component/auxValueCompClient.py
czh_mod/mod/client/component/blockInfoCompClient.py
czh_mod/mod/client/component/blockUseEventWhiteListCompClient.py
czh_mod/mod/client/component/brightnessCompClient.py
czh_mod/mod/client/component/cameraCompClient.py
czh_mod/mod/client/component/chunkSourceCompClient.py
czh_mod/mod/client/component/configCompClient.py
czh_mod/mod/client/component/engineCompFactoryClient.py
czh_mod/mod/client/component/engineTypeCompClient.py
czh_mod/mod/client/component/fogCompClient.py
czh_mod/mod/client/component/frameAniControlComp.py
czh_mod/mod/client/component/frameAniEntityBindComp.py
czh_mod/mod/client/component/frameAniSkeletonBindComp.py
czh_mod/mod/client/component/frameAniTransComp.py
czh_mod/mod/client/component/gameCompClient.py
czh_mod/mod/client/component/healthCompClient.py
czh_mod/mod/client/component/itemCompClient.py
czh_test-1.0.1.dist-info/METADATA
czh_test-1.0.1.dist-info/WHEEL
czh_test-1.0.1.dist-info/top_level.txt
czh_test-1.0.1.dist-info/RECORD
