Metadata-Version: 2.1
Name: czh-test
Version: 1.0.1
Summary: desc
Home-page: https://mc.163.com/dev/mcmanual/mc-dev/mcdocs
Author: UNKNOWN
Author-email: UNKNOWN
License: UNKNOWN
Platform: any
